tsma/__init__.py
tsma/analyses/__init__.py
tsma/analyses/clustering.py
tsma/analyses/metrics.py
tsma/analyses/statistics.py
tsma/analyses/vandin.py
tsma/basics/__init__.py
tsma/basics/text_management.py
tsma/basics/transfers.py
tsma/collect/__init__.py
tsma/collect/data_collect.py
tsma/collect/iterators.py
tsma/collect/output_management.py
tsma/models/__init__.py
tsma/models/gross2022.py
tsma/models/model.py
tsma/visuals/__init__.py
tsma/visuals/dashboards.py
tsma/visuals/fig_constructors.py
tsma/visuals/fig_management.py
tsma/visuals/figures.py
tsma-1.2.0.dist-info/LICENSE
tsma-1.2.0.dist-info/METADATA
tsma-1.2.0.dist-info/WHEEL
tsma-1.2.0.dist-info/top_level.txt
tsma-1.2.0.dist-info/RECORD
