Metadata-Version: 2.1
Name: tsma
Version: 1.2.0
Summary: (time series model analyses) This package offers tools for analyzing models that generate multivariate time series as output.
Home-page: https://github.com/S-bazaz/tsma
Author: S-bazaz
Author-email: sbazazj2@protonmail.com
License: MIT
Keywords: time-series-analysis,phase-diagram,time-series-clustering,simulated-dataset
Classifier: Development Status :: 3 - Alpha
Classifier: Intended Audience :: Developers
Classifier: Intended Audience :: Science/Research
Classifier: Intended Audience :: Financial and Insurance Industry
Classifier: Intended Audience :: Other Audience
Classifier: License :: OSI Approved :: MIT License
Classifier: Natural Language :: English
Classifier: Operating System :: Microsoft :: Windows :: Windows 10
Classifier: Operating System :: OS Independent
Classifier: Programming Language :: Python
Classifier: Programming Language :: Python :: 3
Classifier: Programming Language :: Python :: 3.8
Classifier: Topic :: Scientific/Engineering :: Visualization
Classifier: Topic :: Office/Business :: Financial
Classifier: Framework :: Pytest
Requires-Python: >=3.7
License-File: LICENSE
Requires-Dist: dash (==2.6.1)
Requires-Dist: dash-bootstrap-components (==1.2.1)
Requires-Dist: iisignature (==0.24)
Requires-Dist: jupyter-dash (==0.4.2)
Requires-Dist: matplotlib (==3.5.1)
Requires-Dist: networkx (==2.8.8)
Requires-Dist: numpy (==1.21.5)
Requires-Dist: pandas (==1.4.3)
Requires-Dist: plotly (==5.9.0)
Requires-Dist: scikit-learn (==1.2.0)
Requires-Dist: scipy (==1.7.3)
Requires-Dist: seaborn (==0.11.2)
Requires-Dist: statsmodels (==0.13.2)
Requires-Dist: tqdm (==4.64.0)
Requires-Dist: tslearn (==0.5.2)
